{
  "text": {
    "hey": 26,
    "hello": 25,
    "hi": 27,
    "chào": 15,
    "bạn": 13,
    "xin": 69,
    "buối": 7,
    "sáng": 56,
    "buổi": 8,
    "tối": 64,
    "này": 48,
    "anh": 1,
    "ơi": 79,
    "good": 19,
    "by": 9,
    "cee": 14,
    "you": 71,
    "later": 33,
    "night": 45,
    "bye": 10,
    "goodbye": 20,
    "have": 24,
    "a": 0,
    "nice": 44,
    "day": 18,
    "see": 54,
    "around": 2,
    "bái": 12,
    "bai": 3,
    "tạm": 63,
    "biệt": 6,
    "nhá": 42,
    "hẹn": 30,
    "gặp": 23,
    "lại": 36,
    "vui": 66,
    "vẻ": 67,
    "tốt": 65,
    "lành": 35,
    "đà": 75,
    "nẵng": 49,
    "có": 17,
    "địa": 78,
    "điểm": 74,
    "nào": 47,
    "đẹp": 77,
    "bà": 11,
    "nà": 46,
    "hills": 28,
    "gì": 21,
    "chơi": 16,
    "biển": 5,
    "mỹ": 40,
    "khê": 31,
    "ở": 80,
    "đâu": 76,
    "món": 39,
    "ngon": 41,
    "là": 34,
    "mì": 38,
    "quảng": 53,
    "ăn": 73,
    "nhất": 43,
    "quán": 52,
    "lẩu": 37,
    "nổi": 50,
    "tiếng": 60,
    "thời": 59,
    "tiết": 61,
    "hà": 29,
    "nội": 51,
    "thế": 58,
    "sản": 57,
    "xuất": 70,
    "ô": 72,
    "tô": 62,
    "không": 32,
    "biết": 4,
    "về": 68,
    "sài": 55,
    "gòn": 22
  },
  "intent": {
    "greet": 3,
    "goodbye": 2,
    "ask_location": 1,
    "ask_food": 0,
    "out_of_scope": 4
  },
  "response": null,
  "action_name": {
    "action_listen": 6,
    "action_restart": 7,
    "action_session_start": 9,
    "action_default_fallback": 4,
    "action_deactivate_loop": 1,
    "action_revert_fallback_events": 8,
    "action_default_ask_affirmation": 2,
    "action_default_ask_rephrase": 3,
    "action_two_stage_fallback": 10,
    "action_unlikely_intent": 11,
    "action_back": 0,
    "action_extract_slots": 5,
    "utter_ask_food": 12,
    "utter_ask_location": 13,
    "utter_goodbye": 14,
    "utter_greet": 15,
    "utter_out_of_scope": 16
  },
  "action_text": null,
  "intent_response_key": null
}